tbplots/__init__.py
tbplots/math.py
tbplots/plotting.py
tbplots/tbUtils.py
tbplots-0.1.0.dist-info/LICENSE
tbplots-0.1.0.dist-info/METADATA
tbplots-0.1.0.dist-info/WHEEL
tbplots-0.1.0.dist-info/top_level.txt
tbplots-0.1.0.dist-info/RECORD
