Metadata-Version: 2.1
Name: tbplots
Version: 0.1.0
Summary: A Python Package used to load data from Tensorboard Logs and Plot them.
Home-page: https://github.com/Tran-Research-Group/TB-Plots
Author: Stephen Hudson
Author-email: shudson@anl.gov
License: BSD 2-clause
Platform: UNKNOWN
Classifier: Development Status :: 1 - Planning
Classifier: Intended Audience :: Science/Research
Classifier: License :: OSI Approved :: BSD License
Classifier: Operating System :: POSIX :: Linux
Classifier: Programming Language :: Python :: 2
Classifier: Programming Language :: Python :: 2.7
Classifier: Programming Language :: Python :: 3
Classifier: Programming Language :: Python :: 3.4
Classifier: Programming Language :: Python :: 3.5
Requires-Dist: tensorboard
Requires-Dist: numpy
Requires-Dist: scipy
Requires-Dist: matplotlib
